AUTHORS
LICENSE
MANIFEST.in
README.rst
setup.py
django_sqlserver.egg-info/PKG-INFO
django_sqlserver.egg-info/SOURCES.txt
django_sqlserver.egg-info/dependency_links.txt
django_sqlserver.egg-info/not-zip-safe
django_sqlserver.egg-info/top_level.txt
sqlserver/__init__.py
sqlserver/base.py
sqlserver/base_schema.py
sqlserver/compiler.py
sqlserver/creation.py
sqlserver/fields.py
sqlserver/introspection.py
sqlserver/operations.py
sqlserver/regex_clr.dll
sqlserver/schema.py
sqlserver/south_adapter.py
sqlserver/ado/__init__.py
sqlserver/ado/ado_consts.py
sqlserver/ado/base.py
sqlserver/ado/dbapi.py
sqlserver/ado/introspection.py
sqlserver/ado/patches.py
sqlserver/models/__init__.py
sqlserver/models/manager.py
sqlserver/models/query.py
sqlserver/pymssql/__init__.py
sqlserver/pymssql/base.py
sqlserver/pymssql/introspection.py
sqlserver/pytds/__init__.py
sqlserver/pytds/base.py
sqlserver/pytds/base.py.orig
sqlserver/pytds/introspection.py
sqlserver/sql_app/__init__.py
sqlserver/sql_app/management/__init__.py
sqlserver/sql_app/management/commands/__init__.py
sqlserver/sql_app/management/commands/dbgui.py
sqlserver/sql_app/management/commands/install_regex_clr.py